llm_azure_tts.py
llm_azure_tts-0.1.2.dist-info/LICENSE
llm_azure_tts-0.1.2.dist-info/METADATA
llm_azure_tts-0.1.2.dist-info/WHEEL
llm_azure_tts-0.1.2.dist-info/entry_points.txt
llm_azure_tts-0.1.2.dist-info/top_level.txt
llm_azure_tts-0.1.2.dist-info/RECORD
