Metadata-Version: 2.2
Name: llm-azure-tts
Version: 0.1.2
Summary: Text-to-speech using the Azure OpenAI TTS API
Author: Anwar Ziani
License: Apache-2.0
Project-URL: Homepage, https://github.com/zianwar/llm-azure-tts
Project-URL: Changelog, https://github.com/zianwar/llm-azure-tts/releases
Project-URL: Issues, https://github.com/zianwar/llm-azure-tts/issues
Project-URL: CI, https://github.com/zianwar/llm-azure-tts/actions
Classifier: License :: OSI Approved :: Apache Software License
Requires-Python: >=3.9
License-File: LICENSE
Requires-Dist: llm
Requires-Dist: httpx
Provides-Extra: test
Requires-Dist: pytest; extra == "test"
Requires-Dist: pytest-httpx; extra == "test"
